mpbridge/__init__.py
mpbridge/bridge.py
mpbridge/handler.py
mpbridge/ignore.py
mpbridge/serial_transport.py
mpbridge/shell.py
mpbridge/utils.py
mpbridge-1.6.1.dist-info/LICENSE
mpbridge-1.6.1.dist-info/METADATA
mpbridge-1.6.1.dist-info/WHEEL
mpbridge-1.6.1.dist-info/entry_points.txt
mpbridge-1.6.1.dist-info/top_level.txt
mpbridge-1.6.1.dist-info/RECORD
