Metadata-Version: 2.2
Name: mpbridge
Version: 1.6.1
Summary: File System Bridge to facilitate working with files on Micropython devices
License: MIT License
Project-URL: homepage, https://github.com/AmirHmZz/mpbridge
Keywords: micropython,filemanager,file-manager,filesystem,sync,synchronize
Classifier: Programming Language :: Python
Classifier: Operating System :: OS Independent
Requires-Python: >=3.9
License-File: LICENSE
Requires-Dist: watchdog>=2.2.0
Requires-Dist: colorama>=0.4.0
Requires-Dist: mpremote<=1.22.0,>=1.21.0
Requires-Dist: click
